{
  "id": "vickymenage-post-020",
  "profileId": "vickymenage",
  "title": "Dangerously irresistible. Dare to handle? / Perigosamente irresistível. Vai encarar?",
  "description": "Dangerously irresistible. Dare to handle? / Perigosamente irresistível. Vai encarar?",
  "imageUrl": "https://pbs.twimg.com/media/GyqAW92XMAIXd2-.jpg",
  "tags": [
    "brazil",
    "latina",
    "exclusive",
    "premium",
    "vicky",
    "menage"
  ],
  "postedAt": "2025-06-07T20:29:09.324Z",
  "contentType": "image",
  "likes": 429,
  "views": 1080,
  "sourcePage": "page1",
  "sourceUrl": "https://www.twpornstars.com/vickymenage"
}