{
  "id": "belle-053",
  "title": "Neon Nights 🌈⚡",
  "description": "Exclusive gamer girl content featuring neon nights. Perfect blend of kawaii culture and gaming aesthetic.",
  "imageUrl": "https://img.coomer.st/thumbnail/data/22/01/2201be768d2b0a6fa800d6faa07f3a5d472d6ea921f3058c5ff8009307d85fcf.jpg",
  "tags": [
    "Gamer Girl",
    "Kawaii",
    "Gaming",
    "E-Girl",
    "Cosplay",
    "Anime",
    "Alternative"
  ],
  "createdAt": "2025-08-18T12:27:37.689Z",
  "likes": 195,
  "views": 584
}